currency/__init__.py
currency/cache.py
currency/currency.py
currency/data.py
currency/exceptions.py
nh_currency-1.0.1.dist-info/DESCRIPTION.rst
nh_currency-1.0.1.dist-info/METADATA
nh_currency-1.0.1.dist-info/RECORD
nh_currency-1.0.1.dist-info/WHEEL
nh_currency-1.0.1.dist-info/metadata.json
nh_currency-1.0.1.dist-info/top_level.txt
