Metadata-Version: 1.2
Name: nh-currency
Version: 1.0.1
Summary: A python library to convert currency, prettify price and get various currency info
Home-page: https://github.com/NearHuscarl/py-currency
Author: Near Huscarl
Author-email: near.huscarl@gmail.com
License: BSD 3 Clauses
Keywords: currency money financial
Platform: UNKNOWN
Classifier: Development Status :: 4 - Beta
Classifier: Intended Audience :: Developers
Classifier: Topic :: Software Development :: Libraries
Classifier: License :: OSI Approved :: BSD License
Classifier: Programming Language :: Python :: 3
Classifier: Programming Language :: Python :: 3.2
Classifier: Programming Language :: Python :: 3.3
Classifier: Programming Language :: Python :: 3.4
Classifier: Programming Language :: Python :: 3.5
Classifier: Programming Language :: Python :: 3.6
Requires-Python: >=3
